{
	"configurations" : 
	[
		{
			"directories" : 
			[
				{
					"build" : ".",
					"childIndexes" : 
					[
						1,
						5,
						6
					],
					"hasInstallRule" : true,
					"jsonFile" : "directory-.-Debug-d0094a50bb2071803777.json",
					"minimumCMakeVersion" : 
					{
						"string" : "3.16"
					},
					"projectIndex" : 0,
					"source" : ".",
					"targetIndexes" : 
					[
						2
					]
				},
				{
					"build" : "thirdparty/raylib-5.0",
					"childIndexes" : 
					[
						2
					],
					"hasInstallRule" : true,
					"jsonFile" : "directory-thirdparty.raylib-5.0-Debug-c6c6c3c9ac3db7786b41.json",
					"minimumCMakeVersion" : 
					{
						"string" : "3.0"
					},
					"parentIndex" : 0,
					"projectIndex" : 1,
					"source" : "thirdparty/raylib-5.0",
					"targetIndexes" : 
					[
						5
					]
				},
				{
					"build" : "thirdparty/raylib-5.0/raylib",
					"childIndexes" : 
					[
						3
					],
					"hasInstallRule" : true,
					"jsonFile" : "directory-thirdparty.raylib-5.0.raylib-Debug-e22f260155a0fdc5e7dd.json",
					"minimumCMakeVersion" : 
					{
						"string" : "3.0"
					},
					"parentIndex" : 1,
					"projectIndex" : 1,
					"source" : "thirdparty/raylib-5.0/src",
					"targetIndexes" : 
					[
						3
					]
				},
				{
					"build" : "thirdparty/raylib-5.0/raylib/external/glfw",
					"childIndexes" : 
					[
						4
					],
					"jsonFile" : "directory-thirdparty.raylib-5.0.raylib.external.glfw-Debug-474d3c704f49ce4bc4f0.json",
					"minimumCMakeVersion" : 
					{
						"string" : "3.4"
					},
					"parentIndex" : 2,
					"projectIndex" : 2,
					"source" : "thirdparty/raylib-5.0/src/external/glfw"
				},
				{
					"build" : "thirdparty/raylib-5.0/raylib/external/glfw/src",
					"jsonFile" : "directory-thirdparty.raylib-5.0.raylib.external.glfw.src-Debug-7fd1a4adef00d6dc787a.json",
					"minimumCMakeVersion" : 
					{
						"string" : "3.4"
					},
					"parentIndex" : 3,
					"projectIndex" : 2,
					"source" : "thirdparty/raylib-5.0/src/external/glfw/src",
					"targetIndexes" : 
					[
						0,
						6
					]
				},
				{
					"build" : "thirdparty/imgui-docking",
					"jsonFile" : "directory-thirdparty.imgui-docking-Debug-2d492c23c69eb90a2a2a.json",
					"minimumCMakeVersion" : 
					{
						"string" : "3.1"
					},
					"parentIndex" : 0,
					"projectIndex" : 3,
					"source" : "thirdparty/imgui-docking",
					"targetIndexes" : 
					[
						1
					]
				},
				{
					"build" : "thirdparty/rlImGui",
					"jsonFile" : "directory-thirdparty.rlImGui-Debug-810c86b535e808cb92db.json",
					"minimumCMakeVersion" : 
					{
						"string" : "3.1"
					},
					"parentIndex" : 0,
					"projectIndex" : 4,
					"source" : "thirdparty/rlImGui",
					"targetIndexes" : 
					[
						4
					]
				}
			],
			"name" : "Debug",
			"projects" : 
			[
				{
					"childIndexes" : 
					[
						1,
						3,
						4
					],
					"directoryIndexes" : 
					[
						0
					],
					"name" : "mygame",
					"targetIndexes" : 
					[
						2
					]
				},
				{
					"childIndexes" : 
					[
						2
					],
					"directoryIndexes" : 
					[
						1,
						2
					],
					"name" : "raylib",
					"parentIndex" : 0,
					"targetIndexes" : 
					[
						3,
						5
					]
				},
				{
					"directoryIndexes" : 
					[
						3,
						4
					],
					"name" : "GLFW",
					"parentIndex" : 1,
					"targetIndexes" : 
					[
						0,
						6
					]
				},
				{
					"directoryIndexes" : 
					[
						5
					],
					"name" : "imgui",
					"parentIndex" : 0,
					"targetIndexes" : 
					[
						1
					]
				},
				{
					"directoryIndexes" : 
					[
						6
					],
					"name" : "rlimgui",
					"parentIndex" : 0,
					"targetIndexes" : 
					[
						4
					]
				}
			],
			"targets" : 
			[
				{
					"directoryIndex" : 4,
					"id" : "glfw::@7d621aed3b7f11e3471d",
					"jsonFile" : "target-glfw-Debug-e9f922bf0a43f2eba5bf.json",
					"name" : "glfw",
					"projectIndex" : 2
				},
				{
					"directoryIndex" : 5,
					"id" : "imgui::@0e4bebfa6e0abb85058b",
					"jsonFile" : "target-imgui-Debug-b67f2d57ff1fb7f8a742.json",
					"name" : "imgui",
					"projectIndex" : 3
				},
				{
					"directoryIndex" : 0,
					"id" : "mygame::@6890427a1f51a3e7e1df",
					"jsonFile" : "target-mygame-Debug-d9658650ac9993df917c.json",
					"name" : "mygame",
					"projectIndex" : 0
				},
				{
					"directoryIndex" : 2,
					"id" : "raylib::@dd0063249b2156dc70e7",
					"jsonFile" : "target-raylib-Debug-465c33379db9480bb961.json",
					"name" : "raylib",
					"projectIndex" : 1
				},
				{
					"directoryIndex" : 6,
					"id" : "rlimgui::@6782960d395d4fb82830",
					"jsonFile" : "target-rlimgui-Debug-d58ebada8ca635ebad67.json",
					"name" : "rlimgui",
					"projectIndex" : 4
				},
				{
					"directoryIndex" : 1,
					"id" : "uninstall::@77e4a86643cb06223736",
					"jsonFile" : "target-uninstall-Debug-4cbed57a22c693c3474a.json",
					"name" : "uninstall",
					"projectIndex" : 1
				},
				{
					"directoryIndex" : 4,
					"id" : "update_mappings::@7d621aed3b7f11e3471d",
					"jsonFile" : "target-update_mappings-Debug-6ff23d82d7a71aff79a3.json",
					"name" : "update_mappings",
					"projectIndex" : 2
				}
			]
		}
	],
	"kind" : "codemodel",
	"paths" : 
	{
		"build" : "C:/Users/elias/Downloads/GameChallenge/raylibCmakeSetup-master/out/build/x64-debug",
		"source" : "C:/Users/elias/Downloads/GameChallenge/raylibCmakeSetup-master"
	},
	"version" : 
	{
		"major" : 2,
		"minor" : 6
	}
}
